html4vision/__init__.py
html4vision/_version.py
html4vision/common.py
html4vision/dragColumns.js
html4vision/limitImgLoad.js
html4vision/matchCol.js
html4vision/overlayToggle.js
html4vision/scaleImg.js
html4vision/server.py
html4vision/table.py
html4vision/thumbs.py
html4vision/tile.py
html4vision-0.6.1.dist-info/licenses/LICENSE.txt
html4vision-0.6.1.dist-info/METADATA
html4vision-0.6.1.dist-info/WHEEL
html4vision-0.6.1.dist-info/top_level.txt
html4vision-0.6.1.dist-info/RECORD
