Metadata-Version: 2.4
Name: HTML4Vision
Version: 0.6.1
Summary: A simple HTML visualization tool for computer vision research
Author-email: "Mengtian (Martin) Li" <martinli.work@gmail.com>
License: MIT
Project-URL: homepage, https://github.com/mtli/HTML4Vision
Keywords: research,computer vision,visualization
Classifier: Development Status :: 4 - Beta
Classifier: Intended Audience :: Science/Research
Classifier: Topic :: Scientific/Engineering :: Visualization
Classifier: License :: OSI Approved :: MIT License
Classifier: Programming Language :: Python :: 3
Requires-Python: >=3.10
License-File: LICENSE.txt
Requires-Dist: Flask
Requires-Dist: dominate
Requires-Dist: Pillow>=9.1
Provides-Extra: dev
Requires-Dist: ruff>=0.9; extra == "dev"
Requires-Dist: mypy>=1.10; extra == "dev"
Dynamic: license-file
